miles_guess-2025.1.0.dist-info/licenses/LICENSE
mlguess/VERSION
mlguess/__init__.py
mlguess/classifier_uq.py
mlguess/pbs.py
mlguess/pit.py
mlguess/plotting.py
mlguess/preprocessing.py
mlguess/regression_metrics.py
mlguess/regression_uq.py
mlguess/reliability.py
mlguess/splitting.py
mlguess/keras/__init__.py
mlguess/keras/callbacks.py
mlguess/keras/data.py
mlguess/keras/layers.py
mlguess/keras/losses.py
mlguess/keras/models.py
mlguess/keras/monte_carlo.py
mlguess/keras/seed.py
mlguess/keras/deprecated/callbacks.py
mlguess/keras/deprecated/losses.py
mlguess/keras/deprecated/models.py
mlguess/tests/__init__.py
mlguess/tests/test_environment.py
mlguess/tests/test_layers.py
mlguess/tests/test_models.py
mlguess/tests/test_pit.py
mlguess/tests/test_torch_checkpoint.py
mlguess/tests/test_torch_model.py
mlguess/torch/__init__.py
mlguess/torch/checkpoint.py
mlguess/torch/class_losses.py
mlguess/torch/distributed.py
mlguess/torch/layers.py
mlguess/torch/mc_dropout.py
mlguess/torch/metrics.py
mlguess/torch/mixed_precision.py
mlguess/torch/models.py
mlguess/torch/regression_losses.py
mlguess/torch/scheduler.py
mlguess/torch/trainer_classifier.py
mlguess/torch/trainer_regression.py
miles_guess-2025.1.0.dist-info/METADATA
miles_guess-2025.1.0.dist-info/WHEEL
miles_guess-2025.1.0.dist-info/top_level.txt
miles_guess-2025.1.0.dist-info/RECORD
