Metadata-Version: 2.4
Name: miles-guess
Version: 2025.1.0
Author-email: University Corporation for Atmospheric Research <milescore@ucar.edu>
License: Creative Commons Legal Code
Requires-Python: >=3.8
License-File: LICENSE
Requires-Dist: numpy
Requires-Dist: scipy
Requires-Dist: matplotlib
Requires-Dist: pandas
Requires-Dist: xarray
Requires-Dist: keras
Requires-Dist: scikit-learn
Requires-Dist: netcdf4
Requires-Dist: pyyaml
Requires-Dist: tqdm
Requires-Dist: sphinx
Requires-Dist: numba
Requires-Dist: properscoring
Requires-Dist: pyarrow
Requires-Dist: imbalanced-learn
Requires-Dist: bridgescaler
Requires-Dist: echo-opt
Requires-Dist: hagelslag
Requires-Dist: jupyter
Requires-Dist: nbsphinx
Requires-Dist: myst_parser
Requires-Dist: sphinx_book_theme
Requires-Dist: hagelslag
Provides-Extra: tensorflow
Requires-Dist: tensorflow>=2.16.0; extra == "tensorflow"
Provides-Extra: tensorflow-gpu
Requires-Dist: tensorflow[and-cuda]>=2.16.0; extra == "tensorflow-gpu"
Provides-Extra: torch
Requires-Dist: torch; extra == "torch"
Requires-Dist: safetensors; extra == "torch"
Provides-Extra: jax
Requires-Dist: jax; extra == "jax"
Dynamic: license-file
